popmessage/__init__.py
popmessage/popmsg.py
popmessage-1.0.0.dist-info/licenses/LICENSE
popmessage-1.0.0.dist-info/METADATA
popmessage-1.0.0.dist-info/WHEEL
popmessage-1.0.0.dist-info/top_level.txt
popmessage-1.0.0.dist-info/RECORD
