Metadata-Version: 2.4
Name: popmessage
Version: 1.0.0
Summary: A package that allows developers to create popup messages to aid in debugging and add some spice into their coding process.
Author: Jessica Chen, Catherine Huang
Author-email: Maya Humston <mayahumston@gmail.com>, Shamaamah Ahmad <shamaamah.ahmad@gmail.com>
License:                     GNU GENERAL PUBLIC LICENSE
Project-URL: Homepage, https://github.com/software-students-spring2025/3-python-package-push-then-pull/
Project-URL: Issues, https://github.com/software-students-spring2025/3-python-package-push-then-pull/issues
Classifier: Programming Language :: Python :: 3
Classifier: Operating System :: OS Independent
Classifier: License :: OSI Approved :: GNU General Public License v3 (GPLv3)
Requires-Python: >=3.10
License-File: LICENSE
Requires-Dist: kivy[base]
Requires-Dist: kivy_examples
Requires-Dist: pytest
Dynamic: license-file
